MANIFEST.in
README.rst
setup.cfg
setup.py
tox_run_command.py
tox_run_command.egg-info/PKG-INFO
tox_run_command.egg-info/SOURCES.txt
tox_run_command.egg-info/dependency_links.txt
tox_run_command.egg-info/entry_points.txt
tox_run_command.egg-info/pbr.json
tox_run_command.egg-info/requires.txt
tox_run_command.egg-info/top_level.txt