Metadata-Version: 1.1
Name: tox-run-command
Version: 0.4
Summary: tox plugin to run arbitrary commands in a virtualenv
Home-page: https://github.com/dstanek/tox-run-command
Author: David Stanek
Author-email: dstanek@dstanek.com
License: Apache Software License
Platform: UNKNOWN
Classifier: Development Status :: 3 - Alpha
Classifier: Intended Audience :: Developers
Classifier: License :: OSI Approved :: Apache Software License
Classifier: Natural Language :: English
Classifier: Operating System :: OS Independent
Classifier: Programming Language :: Python
Classifier: Topic :: Software Development :: Testing
